pyenest
