Metadata-Version: 1.0
Name: pyenest
Version: 0.5
Summary: Python API for Nest Thermostat - Edited
Home-page: http://www.github.com/eae
Author: Eugene Efremov
Author-email: eaefremov@gmail.com
License: UNKNOWN
Platform: UNKNOWN
